molo.servicedirectory-11.1.0-py3.6-nspkg.pth
molo/manage.py
molo/project/__init__.py
molo/project/settings.py
molo/project/urls.py
molo/project/wsgi.py
molo/servicedirectory/__init__.py
molo/servicedirectory/admin.py
molo/servicedirectory/context_processors.py
molo/servicedirectory/models.py
molo/servicedirectory/settings.py
molo/servicedirectory/tests.py
molo/servicedirectory/urls.py
molo/servicedirectory/views.py
molo/servicedirectory/migrations/__init__.py
molo/servicedirectory/static/servicedirectory/sd-base.css
molo/servicedirectory/templates/servicedirectory/content_base.html
molo/servicedirectory/templates/servicedirectory/home.html
molo/servicedirectory/templates/servicedirectory/location_results.html
molo/servicedirectory/templates/servicedirectory/location_search.html
molo/servicedirectory/templates/servicedirectory/organisation_detail.html
molo/servicedirectory/templates/servicedirectory/organisation_report.html
molo/servicedirectory/templates/servicedirectory/organisation_results.html
molo/servicedirectory/templates/servicedirectory/organisation_self_sms.html
molo/servicedirectory/templates/servicedirectory/organisation_sms.html
molo/servicedirectory/templates/servicedirectory/includes/location_search_form.html
molo/servicedirectory/tests/__init__.py
molo/servicedirectory/tests/test_context_processors.py
molo/servicedirectory/tests/test_views.py
molo.servicedirectory-11.1.0.dist-info/LICENSE
molo.servicedirectory-11.1.0.dist-info/METADATA
molo.servicedirectory-11.1.0.dist-info/WHEEL
molo.servicedirectory-11.1.0.dist-info/namespace_packages.txt
molo.servicedirectory-11.1.0.dist-info/top_level.txt
molo.servicedirectory-11.1.0.dist-info/RECORD
