Metadata-Version: 2.1
Name: molo.servicedirectory
Version: 11.1.0
Summary: This is the molo.servicedirectory project.
Home-page: https://github.com/praekeltfoundation/molo.servicedirectory
Author: Praekelt Foundation
Author-email: dev@praekeltfoundation.org
License: BSD
Keywords: praekelt,mobi,web,django,molo,servicedirectory
Platform: UNKNOWN
Classifier: Intended Audience :: Developers
Classifier: Natural Language :: English
Classifier: Programming Language :: Python :: 3.6
Requires-Dist: molo.core (>=11.0.0)
Requires-Dist: six (<2,>=1)
